fedi_cleaner/__init__.py
fedi_cleaner/__main__.py
fedi_cleaner/cleaner.py
fedi_cleaner/config.py
fedi_cleaner-0.1.4.dist-info/licenses/LICENSE
fedi_cleaner-0.1.4.dist-info/METADATA
fedi_cleaner-0.1.4.dist-info/WHEEL
fedi_cleaner-0.1.4.dist-info/entry_points.txt
fedi_cleaner-0.1.4.dist-info/top_level.txt
fedi_cleaner-0.1.4.dist-info/RECORD
