Metadata-Version: 2.4
Name: fedi-cleaner
Version: 0.1.4
Summary: A tool to help you clean your Fediverse account's following/followers/lists/blocks/mutes/...
Author-email: poesty <poesty7450@gmail.com>
License-Expression: WTFPL
Project-URL: Homepage, https://codeberg.org/poesty/Fedi-Cleaner
Project-URL: Source, https://codeberg.org/poesty/Fedi-Cleaner
Keywords: mastodon,fediverse,cleaner,followers,automation
Classifier: Programming Language :: Python :: 3
Classifier: Programming Language :: Python :: 3.9
Classifier: Topic :: Communications
Classifier: Intended Audience :: End Users/Desktop
Requires-Python: >=3.9
License-File: LICENSE
Requires-Dist: httpx[http2]>=0.28.1
Requires-Dist: mastodon-py>=2.0.1
Requires-Dist: tqdm>=4.67.1
Dynamic: license-file
